{
  "ID": "2046f5ac-59f6-48be-a1c3-93f711f2014a",
  "Version": "2.3.3.0",
  "Name": "ani_viprenzheng",
  "Content": {
    "Content": {
      "Animation": {
        "Duration": 100,
        "Speed": 1.0,
        "Timelines": [
          {
            "ActionTag": 298320263,
            "Property": "FileData",
            "Frames": [
              {
                "TextureFile": {
                  "Type": "MarkedSubImage",
                  "Path": "img/vipkefu/reg_00.png",
                  "Plist": "ani_vipkefu.plist"
                },
                "FrameIndex": 0,
                "Tween": false,
                "ctype": "TextureFrameData"
              },
              {
                "TextureFile": {
                  "Type": "MarkedSubImage",
                  "Path": "img/vipkefu/reg_01.png",
                  "Plist": "ani_vipkefu.plist"
                },
                "FrameIndex": 5,
                "Tween": false,
                "ctype": "TextureFrameData"
              },
              {
                "TextureFile": {
                  "Type": "MarkedSubImage",
                  "Path": "img/vipkefu/reg_02.png",
                  "Plist": "ani_vipkefu.plist"
                },
                "FrameIndex": 10,
                "Tween": false,
                "ctype": "TextureFrameData"
              },
              {
                "TextureFile": {
                  "Type": "MarkedSubImage",
                  "Path": "img/vipkefu/reg_03.png",
                  "Plist": "ani_vipkefu.plist"
                },
                "FrameIndex": 15,
                "Tween": false,
                "ctype": "TextureFrameData"
              },
              {
                "TextureFile": {
                  "Type": "MarkedSubImage",
                  "Path": "img/vipkefu/reg_04.png",
                  "Plist": "ani_vipkefu.plist"
                },
                "FrameIndex": 20,
                "Tween": false,
                "ctype": "TextureFrameData"
              },
              {
                "TextureFile": {
                  "Type": "MarkedSubImage",
                  "Path": "img/vipkefu/reg_05.png",
                  "Plist": "ani_vipkefu.plist"
                },
                "FrameIndex": 25,
                "Tween": false,
                "ctype": "TextureFrameData"
              },
              {
                "TextureFile": {
                  "Type": "MarkedSubImage",
                  "Path": "img/vipkefu/reg_06.png",
                  "Plist": "ani_vipkefu.plist"
                },
                "FrameIndex": 30,
                "Tween": false,
                "ctype": "TextureFrameData"
              },
              {
                "TextureFile": {
                  "Type": "MarkedSubImage",
                  "Path": "img/vipkefu/reg_07.png",
                  "Plist": "ani_vipkefu.plist"
                },
                "FrameIndex": 35,
                "Tween": false,
                "ctype": "TextureFrameData"
              },
              {
                "TextureFile": {
                  "Type": "MarkedSubImage",
                  "Path": "img/vipkefu/reg_08.png",
                  "Plist": "ani_vipkefu.plist"
                },
                "FrameIndex": 40,
                "Tween": false,
                "ctype": "TextureFrameData"
              },
              {
                "TextureFile": {
                  "Type": "MarkedSubImage",
                  "Path": "img/vipkefu/reg_09.png",
                  "Plist": "ani_vipkefu.plist"
                },
                "FrameIndex": 45,
                "Tween": false,
                "ctype": "TextureFrameData"
              }
            ],
            "ctype": "TimelineData"
          },
          {
            "ActionTag": 298320263,
            "Property": "Alpha",
            "Frames": [
              {
                "Value": 0,
                "FrameIndex": 0,
                "EasingData": {
                  "Type": 0
                },
                "ctype": "IntFrameData"
              },
              {
                "Value": 127,
                "FrameIndex": 5,
                "EasingData": {
                  "Type": 0
                },
                "ctype": "IntFrameData"
              },
              {
                "Value": 127,
                "FrameIndex": 45,
                "EasingData": {
                  "Type": 0
                },
                "ctype": "IntFrameData"
              },
              {
                "Value": 0,
                "FrameIndex": 50,
                "EasingData": {
                  "Type": 0
                },
                "ctype": "IntFrameData"
              },
              {
                "Value": 0,
                "FrameIndex": 100,
                "EasingData": {
                  "Type": 0
                },
                "ctype": "IntFrameData"
              }
            ],
            "ctype": "TimelineData"
          }
        ],
        "ctype": "TimelineActionData"
      },
      "AnimationList": [],
      "ObjectData": {
        "Tag": 9,
        "Children": [
          {
            "FileData": {
              "Type": "MarkedSubImage",
              "Path": "img/vipkefu/reg_09.png",
              "Plist": "ani_vipkefu.plist"
            },
            "BlendFunc": {
              "Src": 1,
              "Dst": 1
            },
            "AnchorPoint": {
              "ScaleX": 0.5,
              "ScaleY": 0.5
            },
            "Position": {
              "X": 0.0,
              "Y": 0.0
            },
            "Scale": {
              "ScaleX": 1.0,
              "ScaleY": 1.0
            },
            "CColor": {},
            "IconVisible": false,
            "PrePosition": {
              "X": 0.0,
              "Y": 0.0
            },
            "PreSize": {
              "X": 0.0,
              "Y": 0.0
            },
            "LeftMargin": -100.0,
            "RightMargin": -100.0,
            "TopMargin": -100.0,
            "BottomMargin": -100.0,
            "Tag": 10,
            "ActionTag": 298320263,
            "Size": {
              "X": 200.0,
              "Y": 200.0
            },
            "Alpha": 127,
            "Name": "renzwz",
            "ctype": "SpriteObjectData"
          }
        ],
        "Size": {
          "X": 0.0,
          "Y": 0.0
        },
        "Name": "Node",
        "ctype": "SingleNodeObjectData"
      },
      "UsedResources": [
        "ani_vipkefu.plist",
        "ani_vipkefu.png"
      ],
      "ctype": "GameFileData"
    }
  },
  "Type": "Node"
}