{
  "ID": "cef24431-2dbf-41eb-9d1c-6649500523da",
  "Version": "2.3.4",
  "Name": "tafang_tk1",
  "Content": {
    "Content": {
      "Animation": {
        "Duration": 0,
        "Speed": 1.0,
        "Timelines": [],
        "ctype": "TimelineActionData"
      },
      "AnimationList": [],
      "ObjectData": {
        "Tag": 836,
        "Children": [
          {
            "ClipAble": false,
            "BackColorAlpha": 178,
            "ComboBoxIndex": 1,
            "SingleColor": {
              "R": 0,
              "G": 0,
              "B": 0
            },
            "FirstColor": {
              "R": 150,
              "G": 200
            },
            "EndColor": {},
            "ColorVector": {
              "ScaleY": 1.0
            },
            "Scale9Width": 1,
            "Scale9Height": 1,
            "TouchEnable": true,
            "StretchHeightEnable": true,
            "AnchorPoint": {},
            "Position": {
              "X": 0.0,
              "Y": 0.0
            },
            "Scale": {
              "ScaleX": 1.0,
              "ScaleY": 1.0
            },
            "CColor": {},
            "IconVisible": false,
            "PrePosition": {
              "X": 0.0,
              "Y": 0.0
            },
            "PercentWidthEnable": true,
            "PercentWidthEnabled": true,
            "PreSize": {
              "X": 1.0,
              "Y": 1.0
            },
            "VerticalEdge": "BothEdge",
            "Tag": 805,
            "ActionTag": 1139067466,
            "Size": {
              "X": 640.0,
              "Y": 1136.0
            },
            "Name": "mask$",
            "ctype": "PanelObjectData"
          },
          {
            "ClipAble": false,
            "BackColorAlpha": 102,
            "SingleColor": {
              "R": 150,
              "G": 200
            },
            "FirstColor": {
              "R": 150,
              "G": 200
            },
            "EndColor": {},
            "ColorVector": {
              "ScaleY": 1.0
            },
            "Scale9Width": 1,
            "Scale9Height": 1,
            "AnchorPoint": {
              "ScaleX": 0.5,
              "ScaleY": 0.5
            },
            "Position": {
              "X": 320.0,
              "Y": 568.0
            },
            "Scale": {
              "ScaleX": 1.0,
              "ScaleY": 1.0
            },
            "CColor": {},
            "IconVisible": false,
            "PositionPercentXEnabled": true,
            "PositionPercentYEnabled": true,
            "PrePosition": {
              "X": 0.5,
              "Y": 0.5
            },
            "PreSize": {
              "X": 0.8844,
              "Y": 0.3785
            },
            "LeftMargin": 37.0,
            "RightMargin": 37.0,
            "TopMargin": 353.0,
            "BottomMargin": 353.0,
            "Tag": 117,
            "Children": [
              {
                "FileData": {
                  "Type": "MarkedSubImage",
                  "Path": "img/public/bg_top.png",
                  "Plist": "public.plist"
                },
                "Scale9Enable": true,
                "Scale9OriginX": 21,
                "Scale9OriginY": 21,
                "Scale9Width": 22,
                "Scale9Height": 22,
                "TouchEnable": true,
                "StretchHeightEnable": true,
                "AnchorPoint": {
                  "ScaleX": 0.5,
                  "ScaleY": 0.5
                },
                "Position": {
                  "X": 282.4028,
                  "Y": 216.9997
                },
                "Scale": {
                  "ScaleX": 1.0,
                  "ScaleY": 1.0
                },
                "CColor": {},
                "IconVisible": false,
                "PrePosition": {
                  "X": 0.4989,
                  "Y": 0.5047
                },
                "PreSize": {
                  "X": 0.9965,
                  "Y": 1.0
                },
                "VerticalEdge": "TopEdge",
                "LeftMargin": 0.4028,
                "RightMargin": 1.5972,
                "TopMargin": -1.9997,
                "BottomMargin": 1.9997,
                "Tag": 1488,
                "ActionTag": 1949236205,
                "Size": {
                  "X": 564.0,
                  "Y": 430.0
                },
                "Name": "bg_1",
                "ctype": "ImageViewObjectData"
              },
              {
                "FileData": {
                  "Type": "MarkedSubImage",
                  "Path": "img/shipin/img_sp_2.png",
                  "Plist": "shipin.plist"
                },
                "Scale9Width": 543,
                "Scale9Height": 119,
                "AnchorPoint": {
                  "ScaleX": 0.5,
                  "ScaleY": 0.5
                },
                "Position": {
                  "X": 281.9409,
                  "Y": 170.0
                },
                "Scale": {
                  "ScaleX": 1.0,
                  "ScaleY": 1.0
                },
                "CColor": {},
                "IconVisible": false,
                "PrePosition": {
                  "X": 0.4981,
                  "Y": 0.3953
                },
                "PreSize": {
                  "X": 0.9594,
                  "Y": 0.2767
                },
                "LeftMargin": 10.4409,
                "RightMargin": 12.5591,
                "TopMargin": 200.5,
                "BottomMargin": 110.5,
                "Tag": 361,
                "ActionTag": 556586259,
                "Size": {
                  "X": 543.0,
                  "Y": 119.0
                },
                "Name": "Image_55",
                "ctype": "ImageViewObjectData"
              },
              {
                "FileData": {
                  "Type": "MarkedSubImage",
                  "Path": "img/shipin/img_sp_1.png",
                  "Plist": "shipin.plist"
                },
                "Scale9Width": 145,
                "Scale9Height": 12,
                "AnchorPoint": {
                  "ScaleX": 0.5,
                  "ScaleY": 0.5
                },
                "Position": {
                  "X": 465.3167,
                  "Y": 409.2337
                },
                "Scale": {
                  "ScaleX": 1.0,
                  "ScaleY": 1.0
                },
                "CColor": {},
                "IconVisible": false,
                "PrePosition": {
                  "X": 0.8221,
                  "Y": 0.9517
                },
                "PreSize": {
                  "X": 0.2562,
                  "Y": 0.0279
                },
                "LeftMargin": 392.8167,
                "RightMargin": 28.1833,
                "TopMargin": 14.7663,
                "BottomMargin": 403.2337,
                "Tag": 249,
                "ActionTag": 2029942769,
                "Size": {
                  "X": 145.0,
                  "Y": 12.0
                },
                "Name": "Image_52",
                "ctype": "ImageViewObjectData"
              },
              {
                "FlipX": true,
                "FileData": {
                  "Type": "MarkedSubImage",
                  "Path": "img/shipin/img_sp_1.png",
                  "Plist": "shipin.plist"
                },
                "Scale9Width": 145,
                "Scale9Height": 12,
                "AnchorPoint": {
                  "ScaleX": 0.5,
                  "ScaleY": 0.5
                },
                "Position": {
                  "X": 109.3085,
                  "Y": 409.2337
                },
                "Scale": {
                  "ScaleX": 1.0,
                  "ScaleY": 1.0
                },
                "CColor": {},
                "IconVisible": false,
                "PrePosition": {
                  "X": 0.1931,
                  "Y": 0.9517
                },
                "PreSize": {
                  "X": 0.2562,
                  "Y": 0.0279
                },
                "LeftMargin": 36.8085,
                "RightMargin": 384.1915,
                "TopMargin": 14.7663,
                "BottomMargin": 403.2337,
                "Tag": 250,
                "ActionTag": 1901838597,
                "Size": {
                  "X": 145.0,
                  "Y": 12.0
                },
                "Name": "Image_52_0",
                "ctype": "ImageViewObjectData"
              },
              {
                "IsCustomSize": true,
                "FontSize": 20,
                "LabelText": "",
                "FontResource": {
                  "Type": "Normal",
                  "Path": "img/fnt/fzcyj.ttf",
                  "Plist": ""
                },
                "HorizontalAlignmentType": "HT_Center",
                "VerticalAlignmentType": "VT_Center",
                "OutlineColor": {
                  "G": 0,
                  "B": 0
                },
                "ShadowColor": {
                  "R": 110,
                  "G": 110,
                  "B": 110
                },
                "ShadowOffsetX": 2.0,
                "ShadowOffsetY": -2.0,
                "AnchorPoint": {
                  "ScaleX": 0.5,
                  "ScaleY": 0.5
                },
                "Position": {
                  "X": 284.0808,
                  "Y": 404.7204
                },
                "Scale": {
                  "ScaleX": 1.0,
                  "ScaleY": 1.0
                },
                "CColor": {
                  "G": 211,
                  "B": 93
                },
                "IconVisible": false,
                "PrePosition": {
                  "X": 0.5019,
                  "Y": 0.9412
                },
                "PreSize": {
                  "X": 0.2827,
                  "Y": 0.0698
                },
                "LeftMargin": 204.0808,
                "RightMargin": 201.9192,
                "TopMargin": 10.2796,
                "BottomMargin": 389.7204,
                "Tag": 251,
                "ActionTag": -230943572,
                "Size": {
                  "X": 160.0,
                  "Y": 30.0
                },
                "Name": "Text_48",
                "ctype": "TextObjectData"
              },
              {
                "ClipAble": false,
                "BackColorAlpha": 102,
                "SingleColor": {
                  "R": 150,
                  "G": 200
                },
                "FirstColor": {
                  "R": 150,
                  "G": 200
                },
                "EndColor": {},
                "ColorVector": {
                  "ScaleY": 1.0
                },
                "Scale9Width": 1,
                "Scale9Height": 1,
                "AnchorPoint": {
                  "ScaleX": 0.5,
                  "ScaleY": 0.5
                },
                "Position": {
                  "X": 283.0,
                  "Y": 294.0
                },
                "Scale": {
                  "ScaleX": 0.84,
                  "ScaleY": 0.84
                },
                "CColor": {},
                "IconVisible": false,
                "PositionPercentXEnabled": true,
                "PrePosition": {
                  "X": 0.5,
                  "Y": 0.6837
                },
                "PreSize": {
                  "X": 0.1943,
                  "Y": 0.2558
                },
                "VerticalEdge": "TopEdge",
                "LeftMargin": 228.0,
                "RightMargin": 228.0,
                "TopMargin": 81.0,
                "BottomMargin": 239.0,
                "Tag": 1588,
                "ActionTag": -2116512522,
                "Size": {
                  "X": 110.0,
                  "Y": 110.0
                },
                "Name": "panel_1$",
                "ctype": "PanelObjectData"
              },
              {
                "IsCustomSize": true,
                "FontSize": 20,
                "LabelText": "",
                "FontResource": {
                  "Type": "Normal",
                  "Path": "img/fnt/fzcyj.ttf",
                  "Plist": ""
                },
                "HorizontalAlignmentType": "HT_Center",
                "VerticalAlignmentType": "VT_Center",
                "OutlineColor": {
                  "G": 0,
                  "B": 0
                },
                "ShadowColor": {
                  "R": 110,
                  "G": 110,
                  "B": 110
                },
                "ShadowOffsetX": 2.0,
                "ShadowOffsetY": -2.0,
                "AnchorPoint": {
                  "ScaleX": 0.5,
                  "ScaleY": 0.5
                },
                "Position": {
                  "X": 283.0,
                  "Y": 364.0
                },
                "Scale": {
                  "ScaleX": 1.0,
                  "ScaleY": 1.0
                },
                "CColor": {
                  "R": 219,
                  "G": 208,
                  "B": 181
                },
                "IconVisible": false,
                "PositionPercentXEnabled": true,
                "PrePosition": {
                  "X": 0.5,
                  "Y": 0.8465
                },
                "PreSize": {
                  "X": 0.8127,
                  "Y": 0.0698
                },
                "LeftMargin": 53.0,
                "RightMargin": 53.0,
                "TopMargin": 51.0,
                "BottomMargin": 349.0,
                "Tag": 254,
                "ActionTag": -967775266,
                "Size": {
                  "X": 460.0,
                  "Y": 30.0
                },
                "Name": "panel_sp_mz$",
                "ctype": "TextObjectData"
              },
              {
                "ClipAble": false,
                "BackColorAlpha": 102,
                "SingleColor": {
                  "R": 150,
                  "G": 200
                },
                "FirstColor": {
                  "R": 150,
                  "G": 200
                },
                "EndColor": {},
                "ColorVector": {
                  "ScaleY": 1.0
                },
                "Scale9Width": 1,
                "Scale9Height": 1,
                "AnchorPoint": {
                  "ScaleX": 0.5,
                  "ScaleY": 0.5
                },
                "Position": {
                  "X": 396.2,
                  "Y": 92.0
                },
                "Scale": {
                  "ScaleX": 1.0,
                  "ScaleY": 1.0
                },
                "CColor": {},
                "IconVisible": false,
                "PositionPercentXEnabled": true,
                "PrePosition": {
                  "X": 0.7,
                  "Y": 0.214
                },
                "PreSize": {
                  "X": 0.2827,
                  "Y": 0.0698
                },
                "LeftMargin": 316.2,
                "RightMargin": 89.8,
                "TopMargin": 323.0,
                "BottomMargin": 77.0,
                "Tag": 811,
                "ActionTag": 521513208,
                "Size": {
                  "X": 160.0,
                  "Y": 30.0
                },
                "Name": "panel_xh$",
                "ctype": "PanelObjectData"
              },
              {
                "ClipAble": false,
                "BackColorAlpha": 102,
                "SingleColor": {
                  "R": 150,
                  "G": 200
                },
                "FirstColor": {
                  "R": 150,
                  "G": 200
                },
                "EndColor": {},
                "ColorVector": {
                  "ScaleY": 1.0
                },
                "Scale9Width": 1,
                "Scale9Height": 1,
                "AnchorPoint": {
                  "ScaleX": 0.5,
                  "ScaleY": 0.5
                },
                "Position": {
                  "X": 281.5156,
                  "Y": 45.0916
                },
                "Scale": {
                  "ScaleX": 1.0,
                  "ScaleY": 1.0
                },
                "CColor": {},
                "IconVisible": false,
                "PrePosition": {
                  "X": 0.4974,
                  "Y": 0.1049
                },
                "PreSize": {
                  "X": 0.9541,
                  "Y": 0.1395
                },
                "LeftMargin": 11.5156,
                "RightMargin": 14.4844,
                "TopMargin": 354.9084,
                "BottomMargin": 15.0916,
                "Tag": 255,
                "ActionTag": -1237643585,
                "Size": {
                  "X": 540.0,
                  "Y": 60.0
                },
                "Name": "btn_neirong$",
                "ctype": "PanelObjectData"
              },
              {
                "FontSize": 24,
                "ButtonText": "升级",
                "FontResource": {
                  "Type": "Normal",
                  "Path": "img/fnt/fzcyj.ttf",
                  "Plist": ""
                },
                "TextColor": {
                  "R": 47,
                  "G": 87,
                  "B": 25
                },
                "NormalFileData": {
                  "Type": "MarkedSubImage",
                  "Path": "img/public/btn/btn1_on.png",
                  "Plist": "public.plist"
                },
                "Scale9OriginX": 15,
                "Scale9OriginY": 11,
                "Scale9Width": 102,
                "Scale9Height": 38,
                "OutlineColor": {
                  "G": 0,
                  "B": 0
                },
                "ShadowColor": {
                  "R": 110,
                  "G": 110,
                  "B": 110
                },
                "ShadowOffsetX": 2.0,
                "ShadowOffsetY": -2.0,
                "TouchEnable": true,
                "AnchorPoint": {
                  "ScaleX": 0.5,
                  "ScaleY": 0.5
                },
                "Position": {
                  "X": 211.4687,
                  "Y": 45.0
                },
                "Scale": {
                  "ScaleX": 1.0,
                  "ScaleY": 1.0
                },
                "CColor": {},
                "IconVisible": false,
                "PrePosition": {
                  "X": 0.3736,
                  "Y": 0.1047
                },
                "PreSize": {
                  "X": 0.2332,
                  "Y": 0.1395
                },
                "LeftMargin": 145.4687,
                "RightMargin": 288.5313,
                "TopMargin": 355.0,
                "BottomMargin": 15.0,
                "Tag": 256,
                "ActionTag": 1499928008,
                "Size": {
                  "X": 132.0,
                  "Y": 60.0
                },
                "VisibleForFrame": false,
                "Name": "btn_l$",
                "ctype": "ButtonObjectData"
              },
              {
                "FontSize": 24,
                "ButtonText": "出售",
                "FontResource": {
                  "Type": "Normal",
                  "Path": "img/fnt/fzcyj.ttf",
                  "Plist": ""
                },
                "TextColor": {
                  "R": 123,
                  "G": 83,
                  "B": 26
                },
                "NormalFileData": {
                  "Type": "MarkedSubImage",
                  "Path": "img/public/btn/btn2_on.png",
                  "Plist": "public.plist"
                },
                "Scale9OriginX": 15,
                "Scale9OriginY": 11,
                "Scale9Width": 102,
                "Scale9Height": 38,
                "OutlineColor": {
                  "G": 0,
                  "B": 0
                },
                "ShadowColor": {
                  "R": 110,
                  "G": 110,
                  "B": 110
                },
                "ShadowOffsetX": 2.0,
                "ShadowOffsetY": -2.0,
                "TouchEnable": true,
                "AnchorPoint": {
                  "ScaleX": 0.5,
                  "ScaleY": 0.5
                },
                "Position": {
                  "X": 343.9718,
                  "Y": 45.0
                },
                "Scale": {
                  "ScaleX": 1.0,
                  "ScaleY": 1.0
                },
                "CColor": {},
                "IconVisible": false,
                "PrePosition": {
                  "X": 0.6077,
                  "Y": 0.1047
                },
                "PreSize": {
                  "X": 0.2332,
                  "Y": 0.1395
                },
                "LeftMargin": 277.9718,
                "RightMargin": 156.0282,
                "TopMargin": 355.0,
                "BottomMargin": 15.0,
                "Tag": 334,
                "ActionTag": 1591424612,
                "Size": {
                  "X": 132.0,
                  "Y": 60.0
                },
                "VisibleForFrame": false,
                "Name": "btn_h$",
                "ctype": "ButtonObjectData"
              },
              {
                "ClipAble": false,
                "BackColorAlpha": 102,
                "SingleColor": {
                  "R": 150,
                  "G": 200
                },
                "FirstColor": {
                  "R": 150,
                  "G": 200
                },
                "EndColor": {},
                "ColorVector": {
                  "ScaleY": 1.0
                },
                "Scale9Width": 1,
                "Scale9Height": 1,
                "AnchorPoint": {
                  "ScaleX": 0.5,
                  "ScaleY": 0.5
                },
                "Position": {
                  "X": 283.0,
                  "Y": 170.0
                },
                "Scale": {
                  "ScaleX": 1.0,
                  "ScaleY": 1.0
                },
                "CColor": {},
                "IconVisible": false,
                "PositionPercentXEnabled": true,
                "PrePosition": {
                  "X": 0.5,
                  "Y": 0.3953
                },
                "PreSize": {
                  "X": 0.9541,
                  "Y": 0.2558
                },
                "LeftMargin": 13.0,
                "RightMargin": 13.0,
                "TopMargin": 205.0,
                "BottomMargin": 115.0,
                "Tag": 362,
                "Children": [
                  {
                    "ClipAble": false,
                    "BackColorAlpha": 102,
                    "SingleColor": {
                      "R": 150,
                      "G": 200
                    },
                    "FirstColor": {
                      "R": 150,
                      "G": 200
                    },
                    "EndColor": {},
                    "ColorVector": {
                      "ScaleY": 1.0
                    },
                    "Scale9Width": 1,
                    "Scale9Height": 1,
                    "AnchorPoint": {
                      "ScaleX": 0.5,
                      "ScaleY": 0.5
                    },
                    "Position": {
                      "X": 135.0,
                      "Y": 77.0
                    },
                    "Scale": {
                      "ScaleX": 1.0,
                      "ScaleY": 1.0
                    },
                    "CColor": {},
                    "IconVisible": false,
                    "PositionPercentXEnabled": true,
                    "PositionPercentYEnabled": true,
                    "PrePosition": {
                      "X": 0.25,
                      "Y": 0.7
                    },
                    "PreSize": {
                      "X": 0.2407,
                      "Y": 0.2727
                    },
                    "LeftMargin": 70.0,
                    "RightMargin": 340.0,
                    "TopMargin": 18.0,
                    "BottomMargin": 62.0,
                    "Tag": 806,
                    "ActionTag": -1042001114,
                    "Size": {
                      "X": 130.0,
                      "Y": 30.0
                    },
                    "Name": "txt_sx1$",
                    "ctype": "PanelObjectData"
                  },
                  {
                    "ClipAble": false,
                    "BackColorAlpha": 102,
                    "SingleColor": {
                      "R": 150,
                      "G": 200
                    },
                    "FirstColor": {
                      "R": 150,
                      "G": 200
                    },
                    "EndColor": {},
                    "ColorVector": {
                      "ScaleY": 1.0
                    },
                    "Scale9Width": 1,
                    "Scale9Height": 1,
                    "AnchorPoint": {
                      "ScaleX": 0.5,
                      "ScaleY": 0.5
                    },
                    "Position": {
                      "X": 135.0,
                      "Y": 33.0
                    },
                    "Scale": {
                      "ScaleX": 1.0,
                      "ScaleY": 1.0
                    },
                    "CColor": {},
                    "IconVisible": false,
                    "PositionPercentXEnabled": true,
                    "PositionPercentYEnabled": true,
                    "PrePosition": {
                      "X": 0.25,
                      "Y": 0.3
                    },
                    "PreSize": {
                      "X": 0.2407,
                      "Y": 0.2727
                    },
                    "LeftMargin": 70.0,
                    "RightMargin": 340.0,
                    "TopMargin": 62.0,
                    "BottomMargin": 18.0,
                    "Tag": 807,
                    "ActionTag": 1858191258,
                    "Size": {
                      "X": 130.0,
                      "Y": 30.0
                    },
                    "Name": "txt_sx2$",
                    "ctype": "PanelObjectData"
                  },
                  {
                    "FileData": {
                      "Type": "MarkedSubImage",
                      "Path": "img/xintafang/img_jt2.png",
                      "Plist": "tafang_1.plist"
                    },
                    "Scale9OriginX": 13,
                    "Scale9OriginY": 9,
                    "Scale9Width": 16,
                    "Scale9Height": 10,
                    "AnchorPoint": {
                      "ScaleX": 0.5,
                      "ScaleY": 0.5
                    },
                    "Position": {
                      "X": 270.0,
                      "Y": 55.0
                    },
                    "Scale": {
                      "ScaleX": 1.0,
                      "ScaleY": 1.0
                    },
                    "CColor": {},
                    "IconVisible": false,
                    "PositionPercentXEnabled": true,
                    "PositionPercentYEnabled": true,
                    "PrePosition": {
                      "X": 0.5,
                      "Y": 0.5
                    },
                    "PreSize": {
                      "X": 0.0778,
                      "Y": 0.2545
                    },
                    "LeftMargin": 249.0,
                    "RightMargin": 249.0,
                    "TopMargin": 41.0,
                    "BottomMargin": 41.0,
                    "Tag": 810,
                    "ActionTag": 1847561876,
                    "Size": {
                      "X": 42.0,
                      "Y": 28.0
                    },
                    "Name": "Image_11",
                    "ctype": "ImageViewObjectData"
                  },
                  {
                    "ClipAble": false,
                    "BackColorAlpha": 102,
                    "SingleColor": {
                      "R": 150,
                      "G": 200
                    },
                    "FirstColor": {
                      "R": 150,
                      "G": 200
                    },
                    "EndColor": {},
                    "ColorVector": {
                      "ScaleY": 1.0
                    },
                    "Scale9Width": 1,
                    "Scale9Height": 1,
                    "AnchorPoint": {
                      "ScaleX": 0.5,
                      "ScaleY": 0.5
                    },
                    "Position": {
                      "X": 405.0,
                      "Y": 77.0
                    },
                    "Scale": {
                      "ScaleX": 1.0,
                      "ScaleY": 1.0
                    },
                    "CColor": {},
                    "IconVisible": false,
                    "PositionPercentXEnabled": true,
                    "PositionPercentYEnabled": true,
                    "PrePosition": {
                      "X": 0.75,
                      "Y": 0.7
                    },
                    "PreSize": {
                      "X": 0.2407,
                      "Y": 0.2727
                    },
                    "LeftMargin": 340.0,
                    "RightMargin": 70.0,
                    "TopMargin": 18.0,
                    "BottomMargin": 62.0,
                    "Tag": 808,
                    "ActionTag": -1937027800,
                    "Size": {
                      "X": 130.0,
                      "Y": 30.0
                    },
                    "Name": "txt_sx3$",
                    "ctype": "PanelObjectData"
                  },
                  {
                    "ClipAble": false,
                    "BackColorAlpha": 102,
                    "SingleColor": {
                      "R": 150,
                      "G": 200
                    },
                    "FirstColor": {
                      "R": 150,
                      "G": 200
                    },
                    "EndColor": {},
                    "ColorVector": {
                      "ScaleY": 1.0
                    },
                    "Scale9Width": 1,
                    "Scale9Height": 1,
                    "AnchorPoint": {
                      "ScaleX": 0.5,
                      "ScaleY": 0.5
                    },
                    "Position": {
                      "X": 405.0,
                      "Y": 33.0
                    },
                    "Scale": {
                      "ScaleX": 1.0,
                      "ScaleY": 1.0
                    },
                    "CColor": {},
                    "IconVisible": false,
                    "PositionPercentXEnabled": true,
                    "PositionPercentYEnabled": true,
                    "PrePosition": {
                      "X": 0.75,
                      "Y": 0.3
                    },
                    "PreSize": {
                      "X": 0.2407,
                      "Y": 0.2727
                    },
                    "LeftMargin": 340.0,
                    "RightMargin": 70.0,
                    "TopMargin": 62.0,
                    "BottomMargin": 18.0,
                    "Tag": 809,
                    "ActionTag": -2127580519,
                    "Size": {
                      "X": 130.0,
                      "Y": 30.0
                    },
                    "Name": "txt_sx4$",
                    "ctype": "PanelObjectData"
                  }
                ],
                "ActionTag": -1499129274,
                "Size": {
                  "X": 540.0,
                  "Y": 110.0
                },
                "VisibleForFrame": false,
                "Name": "zhuangtai1$",
                "ctype": "PanelObjectData"
              },
              {
                "ClipAble": false,
                "BackColorAlpha": 102,
                "SingleColor": {
                  "R": 150,
                  "G": 200
                },
                "FirstColor": {
                  "R": 150,
                  "G": 200
                },
                "EndColor": {},
                "ColorVector": {
                  "ScaleY": 1.0
                },
                "Scale9Width": 1,
                "Scale9Height": 1,
                "AnchorPoint": {
                  "ScaleX": 0.5,
                  "ScaleY": 0.5
                },
                "Position": {
                  "X": 283.0,
                  "Y": 170.0
                },
                "Scale": {
                  "ScaleX": 1.0,
                  "ScaleY": 1.0
                },
                "CColor": {},
                "IconVisible": false,
                "PositionPercentXEnabled": true,
                "PrePosition": {
                  "X": 0.5,
                  "Y": 0.3953
                },
                "PreSize": {
                  "X": 0.9541,
                  "Y": 0.2558
                },
                "LeftMargin": 13.0,
                "RightMargin": 13.0,
                "TopMargin": 205.0,
                "BottomMargin": 115.0,
                "Tag": 651,
                "Children": [
                  {
                    "ClipAble": false,
                    "BackColorAlpha": 102,
                    "SingleColor": {
                      "R": 150,
                      "G": 200
                    },
                    "FirstColor": {
                      "R": 150,
                      "G": 200
                    },
                    "EndColor": {},
                    "ColorVector": {
                      "ScaleY": 1.0
                    },
                    "Scale9Width": 1,
                    "Scale9Height": 1,
                    "AnchorPoint": {
                      "ScaleX": 0.5,
                      "ScaleY": 0.5
                    },
                    "Position": {
                      "X": 270.0,
                      "Y": 82.995
                    },
                    "Scale": {
                      "ScaleX": 1.0,
                      "ScaleY": 1.0
                    },
                    "CColor": {},
                    "IconVisible": false,
                    "PositionPercentXEnabled": true,
                    "PositionPercentYEnabled": true,
                    "PrePosition": {
                      "X": 0.5,
                      "Y": 0.7545
                    },
                    "PreSize": {
                      "X": 0.2407,
                      "Y": 0.2727
                    },
                    "LeftMargin": 205.0,
                    "RightMargin": 205.0,
                    "TopMargin": 12.005,
                    "BottomMargin": 67.995,
                    "Tag": 812,
                    "ActionTag": -363365329,
                    "Size": {
                      "X": 130.0,
                      "Y": 30.0
                    },
                    "Name": "txt_sx5$",
                    "ctype": "PanelObjectData"
                  },
                  {
                    "ClipAble": false,
                    "BackColorAlpha": 102,
                    "SingleColor": {
                      "R": 150,
                      "G": 200
                    },
                    "FirstColor": {
                      "R": 150,
                      "G": 200
                    },
                    "EndColor": {},
                    "ColorVector": {
                      "ScaleY": 1.0
                    },
                    "Scale9Width": 1,
                    "Scale9Height": 1,
                    "AnchorPoint": {
                      "ScaleX": 0.5,
                      "ScaleY": 0.5
                    },
                    "Position": {
                      "X": 270.0,
                      "Y": 44.0
                    },
                    "Scale": {
                      "ScaleX": 1.0,
                      "ScaleY": 1.0
                    },
                    "CColor": {},
                    "IconVisible": false,
                    "PositionPercentXEnabled": true,
                    "PrePosition": {
                      "X": 0.5,
                      "Y": 0.4
                    },
                    "PreSize": {
                      "X": 0.2407,
                      "Y": 0.2727
                    },
                    "LeftMargin": 205.0,
                    "RightMargin": 205.0,
                    "TopMargin": 51.0,
                    "BottomMargin": 29.0,
                    "Tag": 813,
                    "ActionTag": 1100028484,
                    "Size": {
                      "X": 130.0,
                      "Y": 30.0
                    },
                    "Name": "txt_sx6$",
                    "ctype": "PanelObjectData"
                  },
                  {
                    "IsCustomSize": true,
                    "FontSize": 18,
                    "LabelText": "已升到最高等级",
                    "FontResource": {
                      "Type": "Normal",
                      "Path": "img/fnt/fzcyj.ttf",
                      "Plist": ""
                    },
                    "HorizontalAlignmentType": "HT_Center",
                    "VerticalAlignmentType": "VT_Center",
                    "OutlineColor": {
                      "G": 0,
                      "B": 0
                    },
                    "ShadowColor": {
                      "R": 110,
                      "G": 110,
                      "B": 110
                    },
                    "ShadowOffsetX": 2.0,
                    "ShadowOffsetY": -2.0,
                    "AnchorPoint": {
                      "ScaleX": 0.5,
                      "ScaleY": 0.5
                    },
                    "Position": {
                      "X": 270.0,
                      "Y": 10.0
                    },
                    "Scale": {
                      "ScaleX": 1.0,
                      "ScaleY": 1.0
                    },
                    "CColor": {
                      "R": 137,
                      "G": 82,
                      "B": 49
                    },
                    "IconVisible": false,
                    "PositionPercentXEnabled": true,
                    "PrePosition": {
                      "X": 0.5,
                      "Y": 0.0909
                    },
                    "PreSize": {
                      "X": 0.7037,
                      "Y": 0.2727
                    },
                    "LeftMargin": 80.0,
                    "RightMargin": 80.0,
                    "TopMargin": 85.0,
                    "BottomMargin": -5.0,
                    "Tag": 659,
                    "ActionTag": -120121510,
                    "Size": {
                      "X": 380.0,
                      "Y": 30.0
                    },
                    "Name": "panel_sp_wz3$_0",
                    "ctype": "TextObjectData"
                  }
                ],
                "ActionTag": -1247539110,
                "Size": {
                  "X": 540.0,
                  "Y": 110.0
                },
                "VisibleForFrame": false,
                "Name": "zhuangtai2$",
                "ctype": "PanelObjectData"
              }
            ],
            "ActionTag": -2126701464,
            "Size": {
              "X": 566.0,
              "Y": 430.0
            },
            "Name": "panel_bg$",
            "ctype": "PanelObjectData"
          }
        ],
        "Size": {
          "X": 640.0,
          "Y": 1136.0
        },
        "Name": "Layer",
        "ctype": "LayerObjectData"
      },
      "UsedResources": [
        "img/fnt/fzcyj.ttf",
        "public.plist",
        "public.png",
        "shipin.plist",
        "shipin.png",
        "tafang_1.plist",
        "tafang_1.png"
      ],
      "ctype": "GameFileData"
    }
  },
  "Type": "Layer"
}