{
  "ID": "544475bf-6648-492c-88b7-147bf231815c",
  "Version": "2.3.4",
  "Name": "xinnianhuodong_yyb",
  "Content": {
    "Content": {
      "Animation": {
        "Duration": 0,
        "Speed": 1.0,
        "Timelines": [],
        "ctype": "TimelineActionData"
      },
      "AnimationList": [],
      "ObjectData": {
        "Tag": 836,
        "Children": [
          {
            "ClipAble": false,
            "BackColorAlpha": 178,
            "ComboBoxIndex": 1,
            "SingleColor": {
              "R": 0,
              "G": 0,
              "B": 0
            },
            "FirstColor": {
              "R": 150,
              "G": 200
            },
            "EndColor": {},
            "ColorVector": {
              "ScaleY": 1.0
            },
            "Scale9Width": 1,
            "Scale9Height": 1,
            "TouchEnable": true,
            "StretchHeightEnable": true,
            "AnchorPoint": {
              "ScaleX": 0.5,
              "ScaleY": 0.5
            },
            "Position": {
              "X": 320.0,
              "Y": 568.0
            },
            "Scale": {
              "ScaleX": 1.0,
              "ScaleY": 1.0
            },
            "CColor": {},
            "IconVisible": false,
            "PrePosition": {
              "X": 0.5,
              "Y": 0.5
            },
            "PreSize": {
              "X": 1.0,
              "Y": 1.0
            },
            "VerticalEdge": "BothEdge",
            "Tag": 287,
            "ActionTag": -1063808107,
            "Size": {
              "X": 640.0,
              "Y": 1136.0
            },
            "Name": "mask$",
            "ctype": "PanelObjectData"
          },
          {
            "ClipAble": false,
            "BackColorAlpha": 102,
            "SingleColor": {
              "R": 150,
              "G": 200
            },
            "FirstColor": {
              "R": 150,
              "G": 200
            },
            "EndColor": {},
            "ColorVector": {
              "ScaleY": 1.0
            },
            "Scale9Width": 1,
            "Scale9Height": 1,
            "TouchEnable": true,
            "AnchorPoint": {
              "ScaleX": 0.5,
              "ScaleY": 0.5
            },
            "Position": {
              "X": 319.6746,
              "Y": 569.4767
            },
            "Scale": {
              "ScaleX": 1.0,
              "ScaleY": 1.0
            },
            "CColor": {},
            "IconVisible": false,
            "PrePosition": {
              "X": 0.4995,
              "Y": 0.5013
            },
            "PreSize": {
              "X": 1.0,
              "Y": 0.603
            },
            "VerticalEdge": "BothEdge",
            "LeftMargin": -0.3254,
            "RightMargin": 0.3254,
            "TopMargin": 224.0233,
            "BottomMargin": 226.9767,
            "Tag": 455,
            "Children": [
              {
                "FileData": {
                  "Type": "Normal",
                  "Path": "img/bg/bg_xnhd_yyb.png",
                  "Plist": ""
                },
                "Scale9Enable": true,
                "Scale9OriginX": 21,
                "Scale9OriginY": 21,
                "Scale9Width": 598,
                "Scale9Height": 643,
                "StretchHeightEnable": true,
                "AnchorPoint": {
                  "ScaleX": 0.5,
                  "ScaleY": 0.5
                },
                "Position": {
                  "X": 320.0,
                  "Y": 342.5
                },
                "Scale": {
                  "ScaleX": 1.0,
                  "ScaleY": 1.0
                },
                "CColor": {},
                "IconVisible": false,
                "PositionPercentXEnabled": true,
                "PositionPercentYEnabled": true,
                "PrePosition": {
                  "X": 0.5,
                  "Y": 0.5
                },
                "PreSize": {
                  "X": 1.0,
                  "Y": 1.0
                },
                "Tag": 456,
                "ActionTag": 1413764084,
                "Size": {
                  "X": 640.0,
                  "Y": 685.0
                },
                "Name": "bg_1",
                "ctype": "ImageViewObjectData"
              },
              {
                "FileData": {
                  "Type": "MarkedSubImage",
                  "Path": "img/public/bg_xnhd_xinxi.png",
                  "Plist": "public.plist"
                },
                "Scale9Enable": true,
                "Scale9OriginX": 17,
                "Scale9OriginY": 17,
                "Scale9Width": 20,
                "Scale9Height": 20,
                "AnchorPoint": {
                  "ScaleX": 0.5,
                  "ScaleY": 0.5
                },
                "Position": {
                  "X": 320.0,
                  "Y": 328.8
                },
                "Scale": {
                  "ScaleX": 1.0,
                  "ScaleY": 1.0
                },
                "CColor": {},
                "IconVisible": false,
                "PositionPercentXEnabled": true,
                "PositionPercentYEnabled": true,
                "PrePosition": {
                  "X": 0.5,
                  "Y": 0.48
                },
                "PreSize": {
                  "X": 0.8594,
                  "Y": 0.8029
                },
                "LeftMargin": 45.0,
                "RightMargin": 45.0,
                "TopMargin": 81.2,
                "BottomMargin": 53.8,
                "Tag": 174,
                "ActionTag": -1369793920,
                "Size": {
                  "X": 550.0,
                  "Y": 550.0
                },
                "Name": "Image_6",
                "ctype": "ImageViewObjectData"
              },
              {
                "IsCustomSize": true,
                "FontSize": 30,
                "LabelText": "应援榜",
                "FontResource": {
                  "Type": "Normal",
                  "Path": "img/fnt/fzcyj.ttf",
                  "Plist": ""
                },
                "HorizontalAlignmentType": "HT_Center",
                "VerticalAlignmentType": "VT_Center",
                "OutlineSize": 2,
                "OutlineColor": {
                  "R": 133,
                  "G": 69,
                  "B": 0
                },
                "OutlineEnabled": true,
                "ShadowColor": {
                  "R": 110,
                  "G": 110,
                  "B": 110
                },
                "ShadowOffsetX": 2.0,
                "ShadowOffsetY": -2.0,
                "AnchorPoint": {
                  "ScaleX": 0.5025,
                  "ScaleY": 0.4746
                },
                "Position": {
                  "X": 320.576,
                  "Y": 652.0
                },
                "Scale": {
                  "ScaleX": 1.0,
                  "ScaleY": 1.0
                },
                "CColor": {
                  "G": 223,
                  "B": 112
                },
                "IconVisible": false,
                "PrePosition": {
                  "X": 0.5009,
                  "Y": 0.9518
                },
                "PreSize": {
                  "X": 0.625,
                  "Y": 0.0526
                },
                "HorizontalEdge": "BothEdge",
                "VerticalEdge": "TopEdge",
                "LeftMargin": 119.576,
                "RightMargin": 120.424,
                "TopMargin": 14.0856,
                "BottomMargin": 634.9144,
                "Tag": 458,
                "ActionTag": 623154836,
                "Size": {
                  "X": 400.0,
                  "Y": 36.0
                },
                "Name": "text_1$",
                "ctype": "TextObjectData"
              },
              {
                "IsCustomSize": true,
                "FontSize": 22,
                "LabelText": "冠军赛结束后通过邮件发放",
                "FontResource": {
                  "Type": "Normal",
                  "Path": "img/fnt/fzcyj.ttf",
                  "Plist": ""
                },
                "HorizontalAlignmentType": "HT_Center",
                "VerticalAlignmentType": "VT_Center",
                "OutlineSize": 2,
                "OutlineColor": {
                  "R": 60,
                  "G": 83,
                  "B": 169
                },
                "ShadowColor": {
                  "R": 110,
                  "G": 110,
                  "B": 110
                },
                "ShadowOffsetX": 2.0,
                "ShadowOffsetY": -2.0,
                "AnchorPoint": {
                  "ScaleX": 0.5,
                  "ScaleY": 0.5
                },
                "Position": {
                  "X": 320.0,
                  "Y": 620.0
                },
                "Scale": {
                  "ScaleX": 1.0,
                  "ScaleY": 1.0
                },
                "CColor": {
                  "R": 128,
                  "G": 67,
                  "B": 38
                },
                "IconVisible": false,
                "PositionPercentXEnabled": true,
                "PrePosition": {
                  "X": 0.5,
                  "Y": 0.9051
                },
                "PreSize": {
                  "X": 0.4688,
                  "Y": 0.0438
                },
                "VerticalEdge": "TopEdge",
                "LeftMargin": 170.0,
                "RightMargin": 170.0,
                "TopMargin": 50.0,
                "BottomMargin": 605.0,
                "Tag": 172,
                "ActionTag": 1161097219,
                "Size": {
                  "X": 300.0,
                  "Y": 30.0
                },
                "Name": "txt_rw",
                "ctype": "TextObjectData"
              },
              {
                "IsBounceEnabled": true,
                "InnerNodeSize": {
                  "Width": 540,
                  "Height": 574
                },
                "ScrollDirectionType": "Vertical",
                "ClipAble": true,
                "BackColorAlpha": 102,
                "SingleColor": {
                  "G": 150,
                  "B": 100
                },
                "FirstColor": {
                  "G": 150,
                  "B": 100
                },
                "EndColor": {},
                "ColorVector": {
                  "ScaleY": 1.0
                },
                "Scale9Width": 1,
                "Scale9Height": 1,
                "TouchEnable": true,
                "StretchHeightEnable": true,
                "AnchorPoint": {
                  "ScaleX": 0.5,
                  "ScaleY": 1.0
                },
                "Position": {
                  "X": 320.0,
                  "Y": 594.0
                },
                "Scale": {
                  "ScaleX": 1.0,
                  "ScaleY": 1.0
                },
                "CColor": {},
                "IconVisible": false,
                "PositionPercentXEnabled": true,
                "PrePosition": {
                  "X": 0.5,
                  "Y": 0.8672
                },
                "PreSize": {
                  "X": 0.8438,
                  "Y": 0.7708
                },
                "VerticalEdge": "BothEdge",
                "LeftMargin": 50.0,
                "RightMargin": 50.0,
                "TopMargin": 91.0,
                "BottomMargin": 66.0,
                "Tag": 779,
                "ActionTag": -954943541,
                "Size": {
                  "X": 540.0,
                  "Y": 528.0
                },
                "Name": "scrollview$",
                "ctype": "ScrollViewObjectData"
              },
              {
                "FileData": {
                  "Type": "MarkedSubImage",
                  "Path": "img/public/img_zwnr.png",
                  "Plist": "public.plist"
                },
                "Scale9Width": 216,
                "Scale9Height": 247,
                "AnchorPoint": {
                  "ScaleX": 0.5,
                  "ScaleY": 0.5
                },
                "Position": {
                  "X": 324.9672,
                  "Y": 312.5966
                },
                "Scale": {
                  "ScaleX": 1.0,
                  "ScaleY": 1.0
                },
                "CColor": {},
                "IconVisible": false,
                "PrePosition": {
                  "X": 0.5078,
                  "Y": 0.4563
                },
                "PreSize": {
                  "X": 0.3375,
                  "Y": 0.3606
                },
                "LeftMargin": 216.9672,
                "RightMargin": 207.0328,
                "TopMargin": 248.9034,
                "BottomMargin": 189.0966,
                "Tag": 435,
                "ActionTag": -1888073314,
                "Size": {
                  "X": 216.0,
                  "Y": 247.0
                },
                "VisibleForFrame": false,
                "Name": "img_zwnr$",
                "ctype": "ImageViewObjectData"
              },
              {
                "ClipAble": false,
                "BackColorAlpha": 102,
                "SingleColor": {
                  "R": 150,
                  "G": 200
                },
                "FirstColor": {
                  "R": 150,
                  "G": 200
                },
                "EndColor": {},
                "ColorVector": {
                  "ScaleY": 1.0
                },
                "Scale9Width": 1,
                "Scale9Height": 1,
                "AnchorPoint": {
                  "ScaleX": 0.5
                },
                "Position": {
                  "X": 320.0,
                  "Y": 435.5713
                },
                "Scale": {
                  "ScaleX": 1.0,
                  "ScaleY": 1.0
                },
                "CColor": {},
                "IconVisible": false,
                "PositionPercentXEnabled": true,
                "PrePosition": {
                  "X": 0.5,
                  "Y": 0.6359
                },
                "PreSize": {
                  "X": 0.8438,
                  "Y": 0.1781
                },
                "LeftMargin": 50.0,
                "RightMargin": 50.0,
                "TopMargin": 127.4287,
                "BottomMargin": 435.5713,
                "Tag": 952,
                "Children": [
                  {
                    "FileData": {
                      "Type": "MarkedSubImage",
                      "Path": "img/public/bg_xuanshangrenwu_list.png",
                      "Plist": "public.plist"
                    },
                    "Scale9Enable": true,
                    "Scale9OriginX": 17,
                    "Scale9OriginY": 17,
                    "Scale9Width": 18,
                    "Scale9Height": 19,
                    "AnchorPoint": {
                      "ScaleX": 0.5,
                      "ScaleY": 0.5
                    },
                    "Position": {
                      "X": 270.0,
                      "Y": 61.0
                    },
                    "Scale": {
                      "ScaleX": 1.0,
                      "ScaleY": 1.0
                    },
                    "CColor": {},
                    "IconVisible": false,
                    "PositionPercentXEnabled": true,
                    "PositionPercentYEnabled": true,
                    "PrePosition": {
                      "X": 0.5,
                      "Y": 0.5
                    },
                    "PreSize": {
                      "X": 1.0,
                      "Y": 1.0
                    },
                    "Tag": 953,
                    "ActionTag": -1957442330,
                    "Size": {
                      "X": 540.0,
                      "Y": 122.0
                    },
                    "Name": "bg_list$",
                    "ctype": "ImageViewObjectData"
                  },
                  {
                    "LabelText": "",
                    "LabelBMFontFile_CNB": {
                      "Type": "Normal",
                      "Path": "img/fnt/sz_phb.fnt",
                      "Plist": ""
                    },
                    "AnchorPoint": {
                      "ScaleX": 0.5,
                      "ScaleY": 0.5
                    },
                    "Position": {
                      "X": 30.0,
                      "Y": 61.0
                    },
                    "Scale": {
                      "ScaleX": 1.0,
                      "ScaleY": 1.0
                    },
                    "CColor": {},
                    "IconVisible": false,
                    "PositionPercentYEnabled": true,
                    "PrePosition": {
                      "X": 0.0556,
                      "Y": 0.5
                    },
                    "PreSize": {
                      "X": 0.0,
                      "Y": 0.0
                    },
                    "LeftMargin": 30.0,
                    "RightMargin": 510.0,
                    "TopMargin": 61.0,
                    "BottomMargin": 61.0,
                    "Tag": 253,
                    "ActionTag": 127559397,
                    "Size": {
                      "X": 0.0,
                      "Y": 0.0
                    },
                    "Name": "sz_phb$",
                    "ctype": "TextBMFontObjectData"
                  },
                  {
                    "ClipAble": false,
                    "BackColorAlpha": 102,
                    "SingleColor": {
                      "R": 150,
                      "G": 200
                    },
                    "FirstColor": {
                      "R": 150,
                      "G": 200
                    },
                    "EndColor": {},
                    "ColorVector": {
                      "ScaleY": 1.0
                    },
                    "Scale9Width": 1,
                    "Scale9Height": 1,
                    "AnchorPoint": {
                      "ScaleX": 0.5,
                      "ScaleY": 0.5
                    },
                    "Position": {
                      "X": 95.0,
                      "Y": 61.0
                    },
                    "Scale": {
                      "ScaleX": 0.88,
                      "ScaleY": 0.88
                    },
                    "CColor": {},
                    "IconVisible": false,
                    "PositionPercentYEnabled": true,
                    "PrePosition": {
                      "X": 0.1759,
                      "Y": 0.5
                    },
                    "PreSize": {
                      "X": 0.1852,
                      "Y": 0.8197
                    },
                    "LeftMargin": 45.0,
                    "RightMargin": 395.0,
                    "TopMargin": 11.0,
                    "BottomMargin": 11.0,
                    "Tag": 956,
                    "ActionTag": 1937194432,
                    "Size": {
                      "X": 100.0,
                      "Y": 100.0
                    },
                    "Name": "panel_tx$",
                    "ctype": "PanelObjectData"
                  },
                  {
                    "IsCustomSize": true,
                    "FontSize": 22,
                    "LabelText": "",
                    "FontResource": {
                      "Type": "Normal",
                      "Path": "img/fnt/fzcyj.ttf",
                      "Plist": ""
                    },
                    "VerticalAlignmentType": "VT_Center",
                    "OutlineColor": {
                      "G": 0,
                      "B": 0
                    },
                    "ShadowColor": {
                      "R": 110,
                      "G": 110,
                      "B": 110
                    },
                    "ShadowOffsetX": 2.0,
                    "ShadowOffsetY": -2.0,
                    "AnchorPoint": {
                      "ScaleY": 1.0
                    },
                    "Position": {
                      "X": 148.0,
                      "Y": 108.0
                    },
                    "Scale": {
                      "ScaleX": 1.0,
                      "ScaleY": 1.0
                    },
                    "CColor": {
                      "R": 190,
                      "G": 94,
                      "B": 48
                    },
                    "IconVisible": false,
                    "PrePosition": {
                      "X": 0.2741,
                      "Y": 0.8852
                    },
                    "PreSize": {
                      "X": 0.5185,
                      "Y": 0.2869
                    },
                    "LeftMargin": 148.0,
                    "RightMargin": 112.0,
                    "TopMargin": 14.0,
                    "BottomMargin": 73.0,
                    "Tag": 957,
                    "ActionTag": -2029267745,
                    "Size": {
                      "X": 280.0,
                      "Y": 35.0
                    },
                    "Name": "txt_name$",
                    "ctype": "TextObjectData"
                  },
                  {
                    "IsCustomSize": true,
                    "FontSize": 22,
                    "LabelText": "",
                    "FontResource": {
                      "Type": "Normal",
                      "Path": "img/fnt/fzcyj.ttf",
                      "Plist": ""
                    },
                    "VerticalAlignmentType": "VT_Center",
                    "OutlineColor": {
                      "G": 0,
                      "B": 0
                    },
                    "ShadowColor": {
                      "R": 110,
                      "G": 110,
                      "B": 110
                    },
                    "ShadowOffsetX": 2.0,
                    "ShadowOffsetY": -2.0,
                    "AnchorPoint": {
                      "ScaleY": 1.0
                    },
                    "Position": {
                      "X": 148.0,
                      "Y": 76.0
                    },
                    "Scale": {
                      "ScaleX": 1.0,
                      "ScaleY": 1.0
                    },
                    "CColor": {
                      "R": 128,
                      "G": 67,
                      "B": 38
                    },
                    "IconVisible": false,
                    "PrePosition": {
                      "X": 0.2741,
                      "Y": 0.623
                    },
                    "PreSize": {
                      "X": 0.5185,
                      "Y": 0.2869
                    },
                    "LeftMargin": 148.0,
                    "RightMargin": 112.0,
                    "TopMargin": 46.0,
                    "BottomMargin": 41.0,
                    "Tag": 958,
                    "ActionTag": -308620858,
                    "Size": {
                      "X": 280.0,
                      "Y": 35.0
                    },
                    "Name": "txt_title$",
                    "ctype": "TextObjectData"
                  },
                  {
                    "IsCustomSize": true,
                    "FontSize": 20,
                    "LabelText": "",
                    "FontResource": {
                      "Type": "Normal",
                      "Path": "img/fnt/fzcyj.ttf",
                      "Plist": ""
                    },
                    "VerticalAlignmentType": "VT_Center",
                    "OutlineColor": {
                      "G": 0,
                      "B": 0
                    },
                    "ShadowColor": {
                      "R": 110,
                      "G": 110,
                      "B": 110
                    },
                    "ShadowOffsetX": 2.0,
                    "ShadowOffsetY": -2.0,
                    "AnchorPoint": {
                      "ScaleY": 0.5
                    },
                    "Position": {
                      "X": 148.0,
                      "Y": 27.0
                    },
                    "Scale": {
                      "ScaleX": 1.0,
                      "ScaleY": 1.0
                    },
                    "CColor": {
                      "R": 190,
                      "G": 94,
                      "B": 48
                    },
                    "IconVisible": false,
                    "PrePosition": {
                      "X": 0.2741,
                      "Y": 0.2213
                    },
                    "PreSize": {
                      "X": 0.5556,
                      "Y": 0.2459
                    },
                    "LeftMargin": 148.0,
                    "RightMargin": 92.0,
                    "TopMargin": 80.0,
                    "BottomMargin": 12.0,
                    "Tag": 961,
                    "ActionTag": 614123399,
                    "Size": {
                      "X": 300.0,
                      "Y": 30.0
                    },
                    "Name": "text_wkj$",
                    "ctype": "TextObjectData"
                  },
                  {
                    "ClipAble": false,
                    "BackColorAlpha": 102,
                    "SingleColor": {
                      "R": 150,
                      "G": 200
                    },
                    "FirstColor": {
                      "R": 150,
                      "G": 200
                    },
                    "EndColor": {},
                    "ColorVector": {
                      "ScaleY": 1.0
                    },
                    "Scale9Width": 1,
                    "Scale9Height": 1,
                    "TouchEnable": true,
                    "AnchorPoint": {
                      "ScaleY": 0.5
                    },
                    "Position": {
                      "X": 356.0,
                      "Y": 61.0
                    },
                    "Scale": {
                      "ScaleX": 0.8,
                      "ScaleY": 0.8
                    },
                    "CColor": {},
                    "IconVisible": false,
                    "PositionPercentYEnabled": true,
                    "PrePosition": {
                      "X": 0.6593,
                      "Y": 0.5
                    },
                    "PreSize": {
                      "X": 0.3889,
                      "Y": 0.8197
                    },
                    "LeftMargin": 356.0,
                    "RightMargin": -26.0,
                    "TopMargin": 11.0,
                    "BottomMargin": 11.0,
                    "Tag": 275,
                    "ActionTag": 1126450501,
                    "Size": {
                      "X": 210.0,
                      "Y": 100.0
                    },
                    "Name": "ico_nr$",
                    "ctype": "PanelObjectData"
                  }
                ],
                "ActionTag": 416846069,
                "Size": {
                  "X": 540.0,
                  "Y": 122.0
                },
                "VisibleForFrame": false,
                "Name": "list$",
                "ctype": "PanelObjectData"
              },
              {
                "ClipAble": false,
                "BackColorAlpha": 102,
                "SingleColor": {
                  "R": 150,
                  "G": 200
                },
                "FirstColor": {
                  "R": 150,
                  "G": 200
                },
                "EndColor": {},
                "ColorVector": {
                  "ScaleY": 1.0
                },
                "Scale9Width": 1,
                "Scale9Height": 1,
                "AnchorPoint": {
                  "ScaleX": 0.5,
                  "ScaleY": 0.5
                },
                "Position": {
                  "X": 203.648,
                  "Y": 546.219
                },
                "Scale": {
                  "ScaleX": 1.0,
                  "ScaleY": 1.0
                },
                "CColor": {},
                "IconVisible": false,
                "PositionPercentXEnabled": true,
                "PositionPercentYEnabled": true,
                "PrePosition": {
                  "X": 0.3182,
                  "Y": 0.7974
                },
                "PreSize": {
                  "X": 0.4063,
                  "Y": 0.0438
                },
                "LeftMargin": 73.648,
                "RightMargin": 306.352,
                "TopMargin": 123.781,
                "BottomMargin": 531.219,
                "CallBackType": "Touch",
                "Tag": 1553,
                "ActionTag": 16942946,
                "Size": {
                  "X": 260.0,
                  "Y": 30.0
                },
                "VisibleForFrame": false,
                "Name": "list_wz$",
                "ctype": "PanelObjectData"
              },
              {
                "IsCustomSize": true,
                "FontSize": 22,
                "LabelText": "我的投票",
                "FontResource": {
                  "Type": "Normal",
                  "Path": "img/fnt/fzcyj.ttf",
                  "Plist": ""
                },
                "VerticalAlignmentType": "VT_Center",
                "OutlineSize": 2,
                "OutlineColor": {
                  "R": 60,
                  "G": 83,
                  "B": 169
                },
                "ShadowColor": {
                  "R": 110,
                  "G": 110,
                  "B": 110
                },
                "ShadowOffsetX": 2.0,
                "ShadowOffsetY": -2.0,
                "AnchorPoint": {
                  "ScaleX": 0.5,
                  "ScaleY": 0.5
                },
                "Position": {
                  "X": 194.432,
                  "Y": 27.0
                },
                "Scale": {
                  "ScaleX": 1.0,
                  "ScaleY": 1.0
                },
                "CColor": {
                  "R": 128,
                  "G": 67,
                  "B": 38
                },
                "IconVisible": false,
                "PositionPercentXEnabled": true,
                "PrePosition": {
                  "X": 0.3038,
                  "Y": 0.0394
                },
                "PreSize": {
                  "X": 0.4688,
                  "Y": 0.0438
                },
                "VerticalEdge": "TopEdge",
                "LeftMargin": 44.432,
                "RightMargin": 295.568,
                "TopMargin": 643.0,
                "BottomMargin": 12.0,
                "Tag": 197,
                "ActionTag": -821947603,
                "Size": {
                  "X": 300.0,
                  "Y": 30.0
                },
                "Name": "txt_tp$",
                "ctype": "TextObjectData"
              },
              {
                "IsCustomSize": true,
                "FontSize": 22,
                "LabelText": "",
                "FontResource": {
                  "Type": "Normal",
                  "Path": "img/fnt/fzcyj.ttf",
                  "Plist": ""
                },
                "HorizontalAlignmentType": "HT_Right",
                "VerticalAlignmentType": "VT_Center",
                "OutlineSize": 2,
                "OutlineColor": {
                  "R": 60,
                  "G": 83,
                  "B": 169
                },
                "ShadowColor": {
                  "R": 110,
                  "G": 110,
                  "B": 110
                },
                "ShadowOffsetX": 2.0,
                "ShadowOffsetY": -2.0,
                "AnchorPoint": {
                  "ScaleX": 0.5,
                  "ScaleY": 0.5
                },
                "Position": {
                  "X": 444.16,
                  "Y": 27.0
                },
                "Scale": {
                  "ScaleX": 1.0,
                  "ScaleY": 1.0
                },
                "CColor": {
                  "R": 128,
                  "G": 67,
                  "B": 38
                },
                "IconVisible": false,
                "PositionPercentXEnabled": true,
                "PrePosition": {
                  "X": 0.694,
                  "Y": 0.0394
                },
                "PreSize": {
                  "X": 0.4688,
                  "Y": 0.0438
                },
                "VerticalEdge": "TopEdge",
                "LeftMargin": 294.16,
                "RightMargin": 45.84,
                "TopMargin": 643.0,
                "BottomMargin": 12.0,
                "Tag": 196,
                "ActionTag": 345825013,
                "Size": {
                  "X": 300.0,
                  "Y": 30.0
                },
                "Name": "txt_ps$",
                "ctype": "TextObjectData"
              }
            ],
            "ActionTag": 730134836,
            "Size": {
              "X": 640.0,
              "Y": 685.0
            },
            "Name": "panel_bg$",
            "ctype": "PanelObjectData"
          }
        ],
        "Size": {
          "X": 640.0,
          "Y": 1136.0
        },
        "Name": "Layer",
        "ctype": "LayerObjectData"
      },
      "UsedResources": [
        "img/bg/bg_xnhd_yyb.png",
        "img/fnt/fzcyj.ttf",
        "img/fnt/sz_phb.fnt",
        "img/fnt/sz_phb.png",
        "public.plist",
        "public.png"
      ],
      "ctype": "GameFileData"
    }
  },
  "Type": "Layer"
}