{
  "ID": "6f0a8933-f2b2-4a54-b2ab-8430f0da88c2",
  "Version": "2.3.4",
  "Name": "buff_chanrao",
  "Content": {
    "Content": {
      "Animation": {
        "Duration": 0,
        "Speed": 1.0,
        "Timelines": [],
        "ctype": "TimelineActionData"
      },
      "AnimationList": [],
      "ObjectData": {
        "Tag": 18,
        "Children": [
          {
            "FileData": {
              "Type": "MarkedSubImage",
              "Path": "img/chanrao_87.png",
              "Plist": "skillani/buff_chanrao.plist"
            },
            "BlendFunc": {
              "Src": 1,
              "Dst": 771
            },
            "AnchorPoint": {
              "ScaleX": 0.5,
              "ScaleY": 0.5
            },
            "Position": {
              "X": 6.0,
              "Y": 96.0
            },
            "Scale": {
              "ScaleX": 1.0,
              "ScaleY": 1.0
            },
            "CColor": {},
            "IconVisible": false,
            "PrePosition": {
              "X": 0.0,
              "Y": 0.0
            },
            "PreSize": {
              "X": 0.0,
              "Y": 0.0
            },
            "LeftMargin": -122.0,
            "RightMargin": -134.0,
            "TopMargin": -224.0,
            "BottomMargin": -32.0,
            "Tag": 19,
            "ActionTag": -1435678091,
            "Size": {
              "X": 256.0,
              "Y": 256.0
            },
            "Name": "chanrao_87_1",
            "ctype": "SpriteObjectData"
          }
        ],
        "Size": {
          "X": 0.0,
          "Y": 0.0
        },
        "Name": "Node",
        "ctype": "SingleNodeObjectData"
      },
      "UsedResources": [
        "skillani/buff_chanrao.plist",
        "skillani/buff_chanrao.png"
      ],
      "ctype": "GameFileData"
    }
  },
  "Type": "Node"
}